<?xml version="1.0" standalone="no"?>

<faction>
	<starting-resources>
		<resource name="gold" amount="3000"/>
		<resource name="wood" amount="3000"/>
		<resource name="stone" amount="1000"/>
	</starting-resources>
	<starting-units>
		<unit name="beehive" amount="1"/>
		<unit name="pyramid" amount="1"/>
		<unit name="slave" amount="3"/>
	</starting-units>

	<music value="true" path="music/asak-jadeflange.ogg"/>
	<ai-behavior>
		<worker-units>
			<unit name="builder" minimum="3"/>
			<unit name="slave" minimum="12"/>
		</worker-units>
		<building-units>
			<unit name="laser_turret" minimum="9" />
			<unit name="beehive" minimum="3" />
			<unit name="cowtapult" minimum="3" />
			<unit name="earth_serpent" minimum="3" />
			<unit name="defense_cannon" minimum="3" />
		</building-units>
		<upgrades>
			<upgrade name="level_2_towers"/>
			<upgrade name="level_3_towers"/>
			<upgrade name="level_4_towers"/>
		</upgrades>
	</ai-behavior>
</faction>


